causal_hub-0.0.3.dist-info/METADATA
causal_hub-0.0.3.dist-info/WHEEL
causal_hub-0.0.3.dist-info/licenses/LICENSE
causal_hub/__init__.py
causal_hub/assets.pyi
causal_hub/causal_hub.pyd
causal_hub/datasets.pyi
causal_hub/estimators.pyi
causal_hub/models.pyi
causal_hub/py.typed
causal_hub-0.0.3.dist-info/RECORD
