Metadata-Version: 2.4
Name: causal-hub
Version: 0.0.3
Classifier: Programming Language :: Rust
Classifier: Programming Language :: Python :: Implementation :: CPython
Classifier: Programming Language :: Python :: Implementation :: PyPy
Requires-Dist: numpy
Requires-Dist: scipy
Requires-Dist: pandas
Requires-Dist: networkx
License-File: LICENSE
Summary: A library for causal models, inference and discovery.
Keywords: causality
Home-Page: https://github.com/AlessioZanga/causal-hub
Author-email: Alessio Zanga <alessio.zanga@outlook.it>
License-Expression: AGPL-3.0-only
Requires-Python: >=3.10
Project-URL: homepage, https://github.com/AlessioZanga/causal-hub
Project-URL: repository, https://github.com/AlessioZanga/causal-hub
Project-URL: documentation, https://causal-hub.readthedocs.io/
